[
    {
        "Date":"2026-01-06",
        "Review":"good \ud83d\udc4d"
    },
    {
        "Date":"2026-01-06",
        "Review":"good"
    },
    {
        "Date":"2026-01-06",
        "Review":"good"
    },
    {
        "Date":"2026-01-06",
        "Review":"worst experience, I got a wrong item and picture clearly shows that, you didn't provide compensation, I don't you should shut down your support team , good for nothing......"
    },
    {
        "Date":"2026-01-06",
        "Review":"soooo much delivery charge \ud83d\ude21\ud83d\ude20\ud83e\udd2c\ud83e\udd2c\ud83e\udd2c\ud83e\udd2c"
    },
    {
        "Date":"2026-01-06",
        "Review":"Good \ud83d\udc4d"
    },
    {
        "Date":"2026-01-06",
        "Review":"Worst technical team and support team. Was one of the early adopters of Swiggy Instamart. Now there's a bug in their app and for any offer or rewards always the minimum amount in cart page shows 1999 unlike welcome offer. I have raised in help and mail. No use. Just horrible team."
    },
    {
        "Date":"2026-01-06",
        "Review":"It is Very High Price Of all The Products In Instamart. In Market Oil Price where 2200rs and In instamart it was around 2355 rs. And After That Delivery Charges , GST , Surge Charge . For Convience Swiggy charged around 250 extra in just one oil tin."
    },
    {
        "Date":"2026-01-06",
        "Review":"good"
    },
    {
        "Date":"2026-01-06",
        "Review":"waste app this I'm ordering more than 10 times every one missing items in the order it's disgusting to see waste waste app this is...."
    },
    {
        "Date":"2026-01-06",
        "Review":"good app"
    },
    {
        "Date":"2026-01-06",
        "Review":"Pathetic and frustrating ! Poor delivery and ETA that changes in every minute"
    },
    {
        "Date":"2026-01-06",
        "Review":"but needs more offers to order regular"
    },
    {
        "Date":"2026-01-06",
        "Review":"well \ud83d\udc4d"
    },
    {
        "Date":"2026-01-06",
        "Review":"good"
    },
    {
        "Date":"2026-01-06",
        "Review":"login problem too much"
    },
    {
        "Date":"2026-01-06",
        "Review":"Best"
    },
    {
        "Date":"2026-01-06",
        "Review":"I am loving it"
    },
    {
        "Date":"2026-01-06",
        "Review":"good"
    },
    {
        "Date":"2026-01-06",
        "Review":"worst app don't buy any thing from Instamart.. they always send expired and cheap quality products.. if we are trying to convey the issue they won't respond properly.. even they won't take back the their products also.. I have ordered konjac rice they sent expired rice i have raised complaint against it.. but they are simply saying it has shelf life so we won't take back.. they hide expiry date with some other stickers. even I have updated pics and videos too.. they are simply saying we won't"
    },
    {
        "Date":"2026-01-06",
        "Review":"good"
    },
    {
        "Date":"2026-01-06",
        "Review":"good"
    },
    {
        "Date":"2026-01-06",
        "Review":"Swiggy should improve its app features. I was just checking fee difference between different payment methods and as i clicked COD order placed, you can confirm at leastonce after that. More than that when i cancelled within 1 sec they denied and no option for call. Now keep sending delivery no when is at the address and i will not order again via swiggy."
    },
    {
        "Date":"2026-01-06",
        "Review":"I am having difficulty understanding why a 1km delivery would require a minimum of 30 minutes,My experience was not satisfactory."
    },
    {
        "Date":"2026-01-06",
        "Review":"cash on delivery is not available Instamart"
    },
    {
        "Date":"2026-01-06",
        "Review":"good \ud83d\ude0a\ud83d\udc4d\ud83c\udffb"
    },
    {
        "Date":"2026-01-06",
        "Review":"excellent"
    },
    {
        "Date":"2026-01-06",
        "Review":"best experience of delivery and quality"
    },
    {
        "Date":"2026-01-06",
        "Review":"worst customer service and support"
    },
    {
        "Date":"2026-01-06",
        "Review":"Nothing to say. Awesome as always....."
    },
    {
        "Date":"2026-01-06",
        "Review":"superb app"
    },
    {
        "Date":"2026-01-06",
        "Review":"worst food delivery app also the coustomer support is worst"
    },
    {
        "Date":"2026-01-06",
        "Review":"good"
    },
    {
        "Date":"2026-01-06",
        "Review":"service sahi nahi hai"
    },
    {
        "Date":"2026-01-06",
        "Review":"on time service"
    },
    {
        "Date":"2026-01-06",
        "Review":"good"
    },
    {
        "Date":"2026-01-06",
        "Review":"wooow"
    },
    {
        "Date":"2026-01-06",
        "Review":"excellent"
    },
    {
        "Date":"2026-01-06",
        "Review":"good service"
    },
    {
        "Date":"2026-01-06",
        "Review":"nicee"
    },
    {
        "Date":"2026-01-06",
        "Review":"goid"
    },
    {
        "Date":"2026-01-06",
        "Review":"good \ud83d\udc4d"
    },
    {
        "Date":"2026-01-06",
        "Review":"nice"
    },
    {
        "Date":"2026-01-06",
        "Review":"good service One complaint is delivery boy doesn't have change"
    },
    {
        "Date":"2026-01-06",
        "Review":"good"
    },
    {
        "Date":"2026-01-06",
        "Review":"nice app"
    },
    {
        "Date":"2026-01-06",
        "Review":"\u2b50 1 Star \u2013 Unacceptable Support Swiggy charged me for an item that was not delivered (missing leg piece) and still refused a refund. This wasn\u2019t about food quality \u2014 it was a paid item missing from the order. Support responded with a generic message instead of a solution. Taking money for undelivered items and denying refunds is unfair and disappointing. Very poor customer support."
    },
    {
        "Date":"2026-01-06",
        "Review":"good app"
    },
    {
        "Date":"2026-01-06",
        "Review":"service very bad,no any customer care all number, email no reply,I have order payment failed money deducted account but no refunded from 1 months"
    },
    {
        "Date":"2026-01-06",
        "Review":"super app"
    },
    {
        "Date":"2026-01-06",
        "Review":"very good"
    },
    {
        "Date":"2026-01-06",
        "Review":"nice"
    },
    {
        "Date":"2026-01-06",
        "Review":"Good"
    },
    {
        "Date":"2026-01-06",
        "Review":"food taste very good \ud83d\ude0b"
    },
    {
        "Date":"2026-01-06",
        "Review":"osm"
    },
    {
        "Date":"2026-01-06",
        "Review":"\ud83d\udc4d"
    },
    {
        "Date":"2026-01-06",
        "Review":"useful app"
    },
    {
        "Date":"2026-01-06",
        "Review":"besides thvfood the delivery service is slower then a turtle the would freeze the timer on the app like- my order is coming in 11 minutes since 1 hour"
    },
    {
        "Date":"2026-01-06",
        "Review":"order delayed \ud83d\ude24 2 hours"
    },
    {
        "Date":"2026-01-06",
        "Review":"good service"
    },
    {
        "Date":"2026-01-06",
        "Review":"good"
    },
    {
        "Date":"2026-01-06",
        "Review":"ok"
    },
    {
        "Date":"2026-01-06",
        "Review":"good"
    },
    {
        "Date":"2026-01-06",
        "Review":"good but not best"
    },
    {
        "Date":"2026-01-06",
        "Review":"nice"
    },
    {
        "Date":"2026-01-06",
        "Review":"fast service"
    },
    {
        "Date":"2026-01-06",
        "Review":"nice"
    },
    {
        "Date":"2026-01-06",
        "Review":"nice"
    },
    {
        "Date":"2026-01-06",
        "Review":"great app but less offer"
    },
    {
        "Date":"2026-01-06",
        "Review":"i never rate apps but Swiggy has been acting strange lately the product was really bad and after complaining I did not get any response and this is really unacceptable"
    },
    {
        "Date":"2026-01-06",
        "Review":"thank you for solving my problem and I refer to use the Swiggy application"
    },
    {
        "Date":"2026-01-06",
        "Review":"Good"
    },
    {
        "Date":"2026-01-06",
        "Review":"very poor service"
    },
    {
        "Date":"2026-01-06",
        "Review":"good and fast app"
    },
    {
        "Date":"2026-01-06",
        "Review":"nice \ud83d\ude42"
    },
    {
        "Date":"2026-01-06",
        "Review":"the support executive are unable to provide any resolution when ever I connect them"
    },
    {
        "Date":"2026-01-06",
        "Review":"nice \ud83d\udc4d"
    },
    {
        "Date":"2026-01-06",
        "Review":"nice"
    },
    {
        "Date":"2026-01-06",
        "Review":"worst customer care support . I had rated 5 star , changed to 1 star on 06.01.26"
    },
    {
        "Date":"2026-01-06",
        "Review":"This is the worst food delivery app ever! Most of the time they don't deliver food on time, even after having black membership. And their response is pathetic!!"
    },
    {
        "Date":"2026-01-06",
        "Review":"very good Swiggy"
    },
    {
        "Date":"2026-01-06",
        "Review":"total froud worst app.full itam not delivered"
    },
    {
        "Date":"2026-01-06",
        "Review":"good"
    },
    {
        "Date":"2026-01-06",
        "Review":"good \ud83d\udc4d"
    },
    {
        "Date":"2026-01-06",
        "Review":"delivery experience is very \ud83d\udc4e"
    },
    {
        "Date":"2026-01-06",
        "Review":"The food quality was really good and tasted fresh. The packaging was neat and secure with no spillage. Delivery was on time and the delivery partner was polite. Overall, a smooth and satisfying experience. Would definitely recommend."
    },
    {
        "Date":"2026-01-06",
        "Review":"good \ud83d\udc4d"
    },
    {
        "Date":"2026-01-06",
        "Review":"very good but ok"
    },
    {
        "Date":"2026-01-06",
        "Review":"super"
    },
    {
        "Date":"2026-01-06",
        "Review":"super service"
    },
    {
        "Date":"2026-01-06",
        "Review":"good"
    },
    {
        "Date":"2026-01-06",
        "Review":"good"
    },
    {
        "Date":"2026-01-06",
        "Review":"nice"
    },
    {
        "Date":"2026-01-06",
        "Review":"best good service"
    },
    {
        "Date":"2026-01-06",
        "Review":"bahut badiya"
    },
    {
        "Date":"2026-01-06",
        "Review":"Worst Customer service... dont get fooled by the advertisements"
    },
    {
        "Date":"2026-01-06",
        "Review":"good"
    },
    {
        "Date":"2026-01-06",
        "Review":"good"
    },
    {
        "Date":"2026-01-06",
        "Review":"app is awesome"
    },
    {
        "Date":"2026-01-06",
        "Review":"Hi chef Glad to you \ud83e\udd24\ud83e\udd24\ud83e\udd24\ud83e\udd24"
    },
    {
        "Date":"2026-01-06",
        "Review":"good"
    },
    {
        "Date":"2026-01-06",
        "Review":"super"
    },
    {
        "Date":"2026-01-06",
        "Review":"it's very well and comfortable to order, and delivery always comes timely."
    },
    {
        "Date":"2026-01-06",
        "Review":"good service"
    },
    {
        "Date":"2026-01-06",
        "Review":"I have to stay hungry for that day in train"
    },
    {
        "Date":"2026-01-06",
        "Review":"it's easy and good"
    },
    {
        "Date":"2026-01-06",
        "Review":"must appp"
    },
    {
        "Date":"2026-01-06",
        "Review":"very useful app"
    },
    {
        "Date":"2026-01-06",
        "Review":"no waste of time very good instamart\ud83e\udd73\ud83e\udd73\ud83e\udd73\ud83d\udc4c\ud83c\udffb"
    },
    {
        "Date":"2026-01-06",
        "Review":"good \ud83d\udc4d"
    },
    {
        "Date":"2026-01-06",
        "Review":"good"
    },
    {
        "Date":"2026-01-06",
        "Review":"good \ud83d\udc4d"
    },
    {
        "Date":"2026-01-06",
        "Review":"Swiggy delivered n wrong order n they r not helping me with d issue simply dodging d question n making it difficult for us to reach out to them.. i paid a larger sum for a order that was v less priced d managers dirn seem to help or assist n they take all d details n just wrap d conversation .pls watch out guys .service is not like before.not helpful or professional at all . Swiggy not helping.. excessively salty food they just ignored by giving excuses i paid d full money n not able to eat it"
    },
    {
        "Date":"2026-01-06",
        "Review":"cool"
    },
    {
        "Date":"2026-01-06",
        "Review":"Nice"
    },
    {
        "Date":"2026-01-06",
        "Review":"not cancelling my order that they themselves placed"
    },
    {
        "Date":"2026-01-06",
        "Review":"good"
    },
    {
        "Date":"2026-01-06",
        "Review":"good"
    },
    {
        "Date":"2026-01-06",
        "Review":"nice"
    },
    {
        "Date":"2026-01-06",
        "Review":"good service"
    },
    {
        "Date":"2026-01-06",
        "Review":"very bad."
    },
    {
        "Date":"2026-01-06",
        "Review":"not value for money"
    },
    {
        "Date":"2026-01-06",
        "Review":"good"
    },
    {
        "Date":"2026-01-06",
        "Review":"but sometimes order is delay"
    },
    {
        "Date":"2026-01-06",
        "Review":"bad experience not good food deleiver"
    },
    {
        "Date":"2026-01-06",
        "Review":"good service"
    },
    {
        "Date":"2026-01-06",
        "Review":"very bad service"
    },
    {
        "Date":"2026-01-06",
        "Review":"fast"
    },
    {
        "Date":"2026-01-06",
        "Review":"nice"
    },
    {
        "Date":"2026-01-06",
        "Review":"super"
    },
    {
        "Date":"2026-01-06",
        "Review":"Nice"
    },
    {
        "Date":"2026-01-06",
        "Review":"good Idea Swiggy"
    },
    {
        "Date":"2026-01-06",
        "Review":"nice food delivery app"
    },
    {
        "Date":"2026-01-06",
        "Review":"good"
    },
    {
        "Date":"2026-01-06",
        "Review":"ok job"
    },
    {
        "Date":"2026-01-06",
        "Review":"you either name it as quarter biriyani. Making fun of customers by titling is as a discount offer... \ud83d\ude02so shame of u swiggy."
    },
    {
        "Date":"2026-01-06",
        "Review":"bring back human customer support at first level instead of stupid automated bots. Customers closing issues out of disgust doesn't mean 100% success."
    },
    {
        "Date":"2026-01-06",
        "Review":"very good"
    },
    {
        "Date":"2026-01-06",
        "Review":"good"
    },
    {
        "Date":"2026-01-06",
        "Review":"good"
    },
    {
        "Date":"2026-01-06",
        "Review":"good \ud83d\udc4d"
    },
    {
        "Date":"2026-01-06",
        "Review":"very nice\ud83d\udc4d"
    },
    {
        "Date":"2026-01-06",
        "Review":"\ud83d\udc4d\ud83d\udc4d"
    },
    {
        "Date":"2026-01-06",
        "Review":"good"
    },
    {
        "Date":"2026-01-06",
        "Review":"good"
    },
    {
        "Date":"2026-01-06",
        "Review":"good one swiggy"
    },
    {
        "Date":"2026-01-06",
        "Review":"best aap"
    },
    {
        "Date":"2026-01-06",
        "Review":"superb"
    },
    {
        "Date":"2026-01-06",
        "Review":"Amazing"
    },
    {
        "Date":"2026-01-06",
        "Review":"The most pathetic unhelpful staff and unhelpful app l, will never use again"
    },
    {
        "Date":"2026-01-06",
        "Review":"Deleivery is very good \ud83d\udcaf"
    },
    {
        "Date":"2026-01-06",
        "Review":"good \ud83d\udc4d"
    },
    {
        "Date":"2026-01-06",
        "Review":"good taste more restarent delivery person good"
    },
    {
        "Date":"2026-01-06",
        "Review":"superb"
    },
    {
        "Date":"2026-01-06",
        "Review":"good \ud83d\udcaf"
    },
    {
        "Date":"2026-01-06",
        "Review":"nice work done \ud83d\udc4d\u2705"
    },
    {
        "Date":"2026-01-06",
        "Review":"bohot mehega hai"
    },
    {
        "Date":"2026-01-06",
        "Review":"good"
    },
    {
        "Date":"2026-01-06",
        "Review":"not even able to login. just says too many login attempts."
    },
    {
        "Date":"2026-01-06",
        "Review":"Platform fee + delivery charges+ tax = Too much"
    },
    {
        "Date":"2026-01-06",
        "Review":"Customer support sucks they charged me 397rs for cancelation unnecessary i contacted the restaurant they told me none of the food was wasted"
    },
    {
        "Date":"2026-01-06",
        "Review":"gud"
    },
    {
        "Date":"2026-01-06",
        "Review":"Waited over an hour for my order, only for Swiggy to cancel it. Customer support was completely unhelpful, failed to understand the issue, and kept asking me to email instead of resolving it on chat. They even refused to end the chat despite multiple requests, clearly to avoid feedback. Very disappointing service."
    },
    {
        "Date":"2026-01-06",
        "Review":"it is confusion to select the order and quantity"
    },
    {
        "Date":"2026-01-06",
        "Review":"best sellers \ud83d\ude01"
    },
    {
        "Date":"2026-01-06",
        "Review":"good"
    },
    {
        "Date":"2026-01-06",
        "Review":"very good"
    },
    {
        "Date":"2026-01-06",
        "Review":"delivery charges are too high.This is india and not west."
    },
    {
        "Date":"2026-01-06",
        "Review":"nice offers"
    },
    {
        "Date":"2026-01-06",
        "Review":"good"
    },
    {
        "Date":"2026-01-06",
        "Review":"Mast Hai"
    },
    {
        "Date":"2026-01-06",
        "Review":"worst service 15 minutes order not yet delivered even in 1 hour... should improve the service or leave the market forever\ud83d\ude4f"
    },
    {
        "Date":"2026-01-06",
        "Review":"great experience"
    },
    {
        "Date":"2026-01-06",
        "Review":"very good"
    },
    {
        "Date":"2026-01-06",
        "Review":"nice deals"
    },
    {
        "Date":"2026-01-06",
        "Review":"excellent \ud83d\udc4c"
    },
    {
        "Date":"2026-01-06",
        "Review":"good service"
    },
    {
        "Date":"2026-01-06",
        "Review":"nice"
    },
    {
        "Date":"2026-01-06",
        "Review":"nice"
    },
    {
        "Date":"2026-01-06",
        "Review":"The worst app. Constant delays, constantly miss certain items, and deliver wrong items too. Better to use any other delivery app. And all of this is despite me using Swiggy Black. DON'T BUY SWIGGY BLACK."
    },
    {
        "Date":"2026-01-06",
        "Review":"super se uper offer, thank you swingy"
    },
    {
        "Date":"2026-01-06",
        "Review":"good"
    },
    {
        "Date":"2026-01-06",
        "Review":"I have received spoilaged food and no reply is given from Swiggy despite multiple reminder through multiple modes."
    },
    {
        "Date":"2026-01-06",
        "Review":"keep more offers"
    },
    {
        "Date":"2026-01-06",
        "Review":"good"
    },
    {
        "Date":"2026-01-06",
        "Review":"nice"
    },
    {
        "Date":"2026-01-06",
        "Review":"good"
    },
    {
        "Date":"2026-01-06",
        "Review":"good"
    },
    {
        "Date":"2026-01-06",
        "Review":"Good"
    },
    {
        "Date":"2026-01-06",
        "Review":"jabardast"
    },
    {
        "Date":"2026-01-06",
        "Review":"good \ud83d\udc4d"
    },
    {
        "Date":"2026-01-06",
        "Review":"it's nice"
    },
    {
        "Date":"2026-01-06",
        "Review":"very nice"
    },
    {
        "Date":"2026-01-06",
        "Review":"worst app. cancellation fee \ud83d\udcaf % of order amount. worst customer care service too"
    },
    {
        "Date":"2026-01-06",
        "Review":"wow"
    },
    {
        "Date":"2026-01-06",
        "Review":"nice"
    },
    {
        "Date":"2026-01-06",
        "Review":"\ud83d\udc4d"
    },
    {
        "Date":"2026-01-06",
        "Review":"customer support is worst."
    },
    {
        "Date":"2026-01-06",
        "Review":"super akka"
    },
    {
        "Date":"2026-01-06",
        "Review":"osm"
    },
    {
        "Date":"2026-01-06",
        "Review":"ok"
    },
    {
        "Date":"2026-01-06",
        "Review":"very bad service"
    },
    {
        "Date":"2026-01-06",
        "Review":"good"
    },
    {
        "Date":"2026-01-06",
        "Review":"very nice \ud83d\udc4c"
    },
    {
        "Date":"2026-01-06",
        "Review":"you are brilliant \ud83d\udc4f \ud83d\ude00"
    },
    {
        "Date":"2026-01-06",
        "Review":"good \ud83d\udc4d"
    },
    {
        "Date":"2026-01-06",
        "Review":"my Instamart issue is not resolved."
    },
    {
        "Date":"2026-01-06",
        "Review":"best app to eat food \ud83d\ude01 every time i use i will be happy \ud83d\ude0a\ud83d\ude01"
    },
    {
        "Date":"2026-01-06",
        "Review":"nice"
    },
    {
        "Date":"2026-01-06",
        "Review":"good 2 years experience"
    },
    {
        "Date":"2026-01-06",
        "Review":"good \ud83d\udc4d"
    },
    {
        "Date":"2026-01-06",
        "Review":"best food aap"
    },
    {
        "Date":"2026-01-06",
        "Review":"worst service and worst customer care"
    },
    {
        "Date":"2026-01-06",
        "Review":"good"
    },
    {
        "Date":"2026-01-06",
        "Review":"\ud83e\udef6\ud83d\udc4d"
    },
    {
        "Date":"2026-01-06",
        "Review":"good"
    },
    {
        "Date":"2026-01-06",
        "Review":"mast hai guys"
    },
    {
        "Date":"2026-01-06",
        "Review":"good"
    },
    {
        "Date":"2026-01-06",
        "Review":"good"
    },
    {
        "Date":"2026-01-06",
        "Review":"yery nice \ud83d\udc4d\ud83d\udc4d\ud83d\udc4d\ud83d\udc4d God bless you"
    },
    {
        "Date":"2026-01-06",
        "Review":"nice \ud83d\udc4d"
    },
    {
        "Date":"2026-01-06",
        "Review":"worst worst experience they treat customers like thier slaves"
    },
    {
        "Date":"2026-01-06",
        "Review":"waste swiggy \ud83e\udd2e\ud83e\udd2e don't order swiggy Maine order diya tha 9: 30 ko abhi tak receive nahin hua 10:31 clock aur vahan per bola tha tumhara order 30 minut mein deliver ho jaega waste of swiggy \ud83e\udd2e"
    },
    {
        "Date":"2026-01-06",
        "Review":"excellent"
    },
    {
        "Date":"2026-01-06",
        "Review":"great"
    },
    {
        "Date":"2026-01-06",
        "Review":"good"
    },
    {
        "Date":"2026-01-06",
        "Review":"awesome"
    },
    {
        "Date":"2026-01-06",
        "Review":"okay"
    },
    {
        "Date":"2026-01-06",
        "Review":"good \ud83d\udc4d"
    },
    {
        "Date":"2026-01-06",
        "Review":"good"
    },
    {
        "Date":"2026-01-06",
        "Review":"very poor service.....after waiting you people cancelled order...."
    },
    {
        "Date":"2026-01-06",
        "Review":"they won't deliver your order on time even though you are a one black customer. i pissed off with their service there is no option to give negative starts that's why I am giving 1 star"
    },
    {
        "Date":"2026-01-06",
        "Review":"super"
    },
    {
        "Date":"2026-01-06",
        "Review":"nice and managed"
    },
    {
        "Date":"2026-01-06",
        "Review":"good job \ud83d\udc4f"
    },
    {
        "Date":"2026-01-06",
        "Review":"very good"
    },
    {
        "Date":"2026-01-06",
        "Review":"Its pathetic, do not use it, no resposibility."
    },
    {
        "Date":"2026-01-06",
        "Review":"good"
    },
    {
        "Date":"2026-01-06",
        "Review":"nice \ud83d\ude0a\ud83d\udc4f"
    },
    {
        "Date":"2026-01-06",
        "Review":"Nice"
    },
    {
        "Date":"2026-01-06",
        "Review":"good\ud83d\udc4d"
    },
    {
        "Date":"2026-01-06",
        "Review":"worst experience prices are very higher"
    },
    {
        "Date":"2026-01-06",
        "Review":"wow"
    },
    {
        "Date":"2026-01-06",
        "Review":"fineservice"
    },
    {
        "Date":"2026-01-06",
        "Review":"nice \ud83d\udc4d\ud83d\udc4d\ud83d\udc4d"
    },
    {
        "Date":"2026-01-06",
        "Review":"good working \ud83d\udc4d"
    },
    {
        "Date":"2026-01-06",
        "Review":"Best"
    },
    {
        "Date":"2026-01-06",
        "Review":"\ud83c\udf41"
    },
    {
        "Date":"2026-01-06",
        "Review":"good"
    },
    {
        "Date":"2026-01-06",
        "Review":"good\ud83d\udc4d\ud83c\udffb"
    },
    {
        "Date":"2026-01-06",
        "Review":"I will never use it again in the future too much delay order rider told me order not ready that is a reason for the delay."
    },
    {
        "Date":"2026-01-06",
        "Review":"Lakhimpur walo iss app ka use na krna"
    },
    {
        "Date":"2026-01-06",
        "Review":"good"
    },
    {
        "Date":"2026-01-06",
        "Review":"payment gateway not working"
    },
    {
        "Date":"2026-01-06",
        "Review":"I ordered dry fruit laddoo but Restaurant sent soan Papdi and when raising complaint over email they say \"we will not be able to help\", not trust worthy application. Now before replying to this review search your email with me name and resolve"
    },
    {
        "Date":"2026-01-06",
        "Review":"worst quality Instamart goods.. I ordered 30 eggs and I got 6 broken eggs and som of eggs got fungi and some colour change.. worst quality and packing .. and I got no help from Swiggy.. worst experience.. is there any chance to give zero stars.. I hate Swiggy.."
    },
    {
        "Date":"2026-01-06",
        "Review":"time 9 call Swiggy life ka line"
    },
    {
        "Date":"2026-01-06",
        "Review":"good \ud83d\udc4d\ud83c\udffb"
    },
    {
        "Date":"2026-01-06",
        "Review":"came back to give a bad review and guess what i had done it already in 2022 stupid app with bugs and worst customer service"
    },
    {
        "Date":"2026-01-06",
        "Review":"nice"
    },
    {
        "Date":"2026-01-06",
        "Review":"Pathetic Service Support"
    },
    {
        "Date":"2026-01-06",
        "Review":"super"
    },
    {
        "Date":"2026-01-06",
        "Review":"Worst App ever Just after purchasing Swiggy One Subscription The Offers from restaurant decreased to nil now . My only Advice to everyone is do not purchase their Swiggy One Subscription."
    },
    {
        "Date":"2026-01-06",
        "Review":"good service.."
    },
    {
        "Date":"2026-01-06",
        "Review":"peisa lut ne ki masi. he"
    },
    {
        "Date":"2026-01-06",
        "Review":"this is worst app sometimes delivery person mussbehave and sometimes they don't come in time sometimes they take someone else order in my adress"
    },
    {
        "Date":"2026-01-06",
        "Review":"that very best service in our world"
    },
    {
        "Date":"2026-01-06",
        "Review":"okay good \ud83d\udc4d\ud83c\udffb"
    },
    {
        "Date":"2026-01-06",
        "Review":"extra charge"
    },
    {
        "Date":"2026-01-06",
        "Review":"super Mario"
    },
    {
        "Date":"2026-01-06",
        "Review":"best"
    },
    {
        "Date":"2026-01-06",
        "Review":"gud"
    },
    {
        "Date":"2026-01-06",
        "Review":"good"
    },
    {
        "Date":"2026-01-06",
        "Review":"fake"
    },
    {
        "Date":"2026-01-06",
        "Review":"good"
    },
    {
        "Date":"2026-01-06",
        "Review":"nice work ,"
    },
    {
        "Date":"2026-01-06",
        "Review":"i just can't express i much i have suffered every time i had ordered anything from here. the frustration is so real that today i just told myself \" bhool kr b Swiggy use nahi krna\" you guys make the customers wait for an hour just to cancel the order when you can't find the delivery partner. just close the app if you can't give a good service. you always ruin my day."
    },
    {
        "Date":"2026-01-06",
        "Review":"must"
    },
    {
        "Date":"2026-01-06",
        "Review":"nice\ud83d\ude1d\ud83d\ude1d\ud83d\ude1d\ud83d\ude1d\ud83d\ude1d"
    },
    {
        "Date":"2026-01-06",
        "Review":"good quality"
    },
    {
        "Date":"2026-01-06",
        "Review":"worst experience....have to wait for 1hr and more for food to get delivered....does not assign the delivery partner fast.... executive don't even respond"
    },
    {
        "Date":"2026-01-06",
        "Review":"too much bad experience batter right now zomato"
    },
    {
        "Date":"2026-01-06",
        "Review":"best app"
    },
    {
        "Date":"2026-01-06",
        "Review":"very nice"
    },
    {
        "Date":"2026-01-06",
        "Review":"ok"
    },
    {
        "Date":"2026-01-06",
        "Review":"its good \ud83d\ude0a"
    },
    {
        "Date":"2026-01-06",
        "Review":"good"
    },
    {
        "Date":"2026-01-06",
        "Review":"super"
    },
    {
        "Date":"2026-01-06",
        "Review":"useless app, in sharing order option it literally delayed my order by 2 hours. Zomato is 100 times better than this"
    },
    {
        "Date":"2026-01-06",
        "Review":"very nice food and very nice delivery"
    },
    {
        "Date":"2026-01-06",
        "Review":"good"
    },
    {
        "Date":"2026-01-06",
        "Review":"superb"
    },
    {
        "Date":"2026-01-06",
        "Review":"excellent"
    },
    {
        "Date":"2026-01-06",
        "Review":"all offer were fake"
    },
    {
        "Date":"2026-01-06",
        "Review":"good"
    },
    {
        "Date":"2026-01-06",
        "Review":"awesome service"
    },
    {
        "Date":"2026-01-06",
        "Review":"VERI NICE AMERJENCY HUNGER"
    },
    {
        "Date":"2026-01-06",
        "Review":"Very disappointed with Swiggy. Late delivery and cold food. Not worth the money."
    },
    {
        "Date":"2026-01-06",
        "Review":"good"
    },
    {
        "Date":"2026-01-06",
        "Review":"Deserves 0 stars, the restaurant had cancelled my order and Swiggy refused to give me a refund despite the restaurant cancelling the order."
    },
    {
        "Date":"2026-01-06",
        "Review":"worst, I wanted to give minus stars for this. They accept order even if payment is not completed. If we want to cancel the order, there is no cancellation option in the app. When I ask customer support to cancel my order then they will ask for 100% cancellation fee. This is a total scam where eventually the customer will have to pay in either of the scenarios. Why it is accepting order even when the payment is not even completed. I will never ever use this app again in future. Scam delivery app."
    },
    {
        "Date":"2026-01-06",
        "Review":"10 minutes time"
    },
    {
        "Date":"2026-01-06",
        "Review":"good"
    },
    {
        "Date":"2026-01-06",
        "Review":"best"
    },
    {
        "Date":"2026-01-06",
        "Review":"bhut acha hai"
    },
    {
        "Date":"2026-01-06",
        "Review":"super"
    },
    {
        "Date":"2026-01-06",
        "Review":"super"
    },
    {
        "Date":"2026-01-06",
        "Review":"pramoyam food"
    },
    {
        "Date":"2026-01-06",
        "Review":"amazing \ud83e\udd29"
    },
    {
        "Date":"2026-01-06",
        "Review":"order received tooo let"
    },
    {
        "Date":"2026-01-06",
        "Review":"great"
    },
    {
        "Date":"2026-01-06",
        "Review":"maha ke jhaatuu hai ye log ye log chor hai is app ko jald uninstall kro"
    },
    {
        "Date":"2026-01-06",
        "Review":"thanks swiggy"
    },
    {
        "Date":"2026-01-06",
        "Review":"good"
    },
    {
        "Date":"2026-01-06",
        "Review":"good"
    },
    {
        "Date":"2026-01-06",
        "Review":"Good"
    },
    {
        "Date":"2026-01-06",
        "Review":"please do not buy anything on this platform it's all cheating and fraud \ud83d\ude2d"
    },
    {
        "Date":"2026-01-06",
        "Review":"best one"
    },
    {
        "Date":"2026-01-06",
        "Review":"very good"
    },
    {
        "Date":"2026-01-06",
        "Review":"worst delivery service always late and no proper response from the team."
    },
    {
        "Date":"2026-01-06",
        "Review":"worst order app. has some great offers but the delivery takes more than 1.5hrs even for 7kms. and the order is always delayed. no cancellation option. no cooperative staff. nothing. order gets cancelled anytime without your option and no compensation nothing. please try zomato or any order food app not Swiggy"
    },
    {
        "Date":"2026-01-06",
        "Review":"superb"
    },
    {
        "Date":"2026-01-06",
        "Review":"good"
    },
    {
        "Date":"2026-01-06",
        "Review":"good"
    },
    {
        "Date":"2026-01-06",
        "Review":"9:49 PM I ordered Food, , 2 hours 1 minute later, the order was cancelled. 11:51 PM The amount was refunded. When I called customer care for the first time, the delivery person did not pick the call. They said they I will arrange another delivery partner for you. The second delivery partner, called me and already picked up your order someone , So what should I do? I called customer care no response worst experience Swiggy ,uninstall Swiggy bye byeee"
    },
    {
        "Date":"2026-01-06",
        "Review":"worst experience \ud83d\ude1eI have already deleted the Swiggy app from my mobile phone and from my family members\u2019 mobile phones as well.I like Swiggy very much, and I have purchased most of my gadgets through Swiggy. Thank you for supporting me over the past few years, but now I feel it was bad and waste.\u201d Thank you....\ud83d\ude4f"
    },
    {
        "Date":"2026-01-06",
        "Review":"good \ud83d\udc4d\ud83d\ude0a"
    },
    {
        "Date":"2026-01-06",
        "Review":"osm"
    },
    {
        "Date":"2026-01-06",
        "Review":"good responce"
    },
    {
        "Date":"2026-01-06",
        "Review":"it's so cool"
    },
    {
        "Date":"2026-01-06",
        "Review":"good"
    },
    {
        "Date":"2026-01-06",
        "Review":"WORST APP EVER. OPENLY SCAMMING. SO MANY TIMES THE ITEMS IN MY ORDER WERE MISSING, OR WRONG ITEMS WERE SENT, OR ITEMS WERE SPILLED ETC, BUT THEY DIDNOT GAVE ANY REFUND!!!! THEY ARE TAKING MONEY WITHOUT GIVING ANY FOOD!!!!THEY TOLD ME THAT WE WILL MAIL YOU BACK IN 3 DAYS BUT NO MAIL CAME ALSO. SWIGGY NOW IS JUST PURE SCAM. I AM FILING AN OFFICIAL COMPLAINT TO NATIONAL CONSUMER HELPLINE (NCH). THESE PEOPLE ARE OPENLY SCAMMING NOW!!"
    },
    {
        "Date":"2026-01-06",
        "Review":"Blocked my account for unknown reasons. No review or help provided. Switching to zomato"
    },
    {
        "Date":"2026-01-06",
        "Review":"\u0917\u0941\u0921"
    },
    {
        "Date":"2026-01-06",
        "Review":"used to love Swiggy earlier,these days prices are way costly and delivery charges are also way higher..it's better to go out and grab the food instead of ordering via swiggy"
    },
    {
        "Date":"2026-01-06",
        "Review":"very best foody app"
    },
    {
        "Date":"2026-01-06",
        "Review":"good but charges high."
    },
    {
        "Date":"2026-01-06",
        "Review":"application good delivery good but Swiggy service totaly bad my issue not resolved"
    },
    {
        "Date":"2026-01-06",
        "Review":"don't use Instamart expered product"
    },
    {
        "Date":"2026-01-06",
        "Review":"Good"
    },
    {
        "Date":"2026-01-06",
        "Review":"nice"
    },
    {
        "Date":"2026-01-06",
        "Review":"good"
    },
    {
        "Date":"2026-01-06",
        "Review":"good delivery"
    },
    {
        "Date":"2026-01-06",
        "Review":"good"
    },
    {
        "Date":"2026-01-06",
        "Review":"poor service"
    },
    {
        "Date":"2026-01-06",
        "Review":"bad"
    },
    {
        "Date":"2026-01-06",
        "Review":"good"
    },
    {
        "Date":"2026-01-06",
        "Review":"very good"
    },
    {
        "Date":"2026-01-06",
        "Review":"thankyou"
    },
    {
        "Date":"2026-01-06",
        "Review":"customer service these days is quite disappointing. It seems like every interaction is handled by a bot, which is quite frustrating. The late replies and lack of assistance from customer service representatives are particularly disheartening. It's clear that customer support is none from swiggy. I hope companies can improve their customer service. ps-i did email you but still swiggy is not accepting his mistake despite clear evidences on photos as always.pathetic service"
    },
    {
        "Date":"2026-01-06",
        "Review":"best \ud83e\udd73\ud83e\udd73"
    },
    {
        "Date":"2026-01-06",
        "Review":"the app is very good you should read this app 5 out of three or four because none of the app is very good to get 5 out of five because none of the app is perfectly good \ud83d\ude0a."
    },
    {
        "Date":"2026-01-06",
        "Review":"not good"
    },
    {
        "Date":"2026-01-06",
        "Review":"less offers"
    },
    {
        "Date":"2026-01-06",
        "Review":"good for long distance"
    },
    {
        "Date":"2026-01-06",
        "Review":"good"
    },
    {
        "Date":"2026-01-06",
        "Review":"good"
    },
    {
        "Date":"2026-01-06",
        "Review":"very good \ud83d\udc4d\ud83c\udffb"
    },
    {
        "Date":"2026-01-06",
        "Review":"ok"
    },
    {
        "Date":"2026-01-06",
        "Review":"I ordered a meal on the 5th, the order was accepted, the delivery boy called me and said he couldn't deliver your meal because the company wasn't paying me much. On the 6th morning, I noticed that my meal wasn't with me."
    },
    {
        "Date":"2026-01-06",
        "Review":"nic"
    },
    {
        "Date":"2026-01-06",
        "Review":"delivery in time and product is too good"
    },
    {
        "Date":"2026-01-06",
        "Review":"fantastic everything \ud83d\ude0d"
    },
    {
        "Date":"2026-01-06",
        "Review":"very bad app \ud83d\ude15 this app food \ud83e\udd2e"
    },
    {
        "Date":"2026-01-06",
        "Review":"worst app for delivery, so many delayed order , and even if I missed an item in the order it didn't solve the problem and told me to send an email , no response to email or anything , once this used to be so good , but now it's not ."
    },
    {
        "Date":"2026-01-06",
        "Review":"very pathetic you Swiggy people, deliver BEEF , from delivery partner's. irrespective of their consent....very disturbing."
    },
    {
        "Date":"2026-01-06",
        "Review":"average"
    },
    {
        "Date":"2026-01-06",
        "Review":"Very useful app for ordering in ."
    },
    {
        "Date":"2026-01-06",
        "Review":"good"
    },
    {
        "Date":"2026-01-06",
        "Review":"good \ud83d\udc4d"
    },
    {
        "Date":"2026-01-06",
        "Review":"good"
    },
    {
        "Date":"2026-01-06",
        "Review":"wrost Customer support"
    },
    {
        "Date":"2026-01-06",
        "Review":"nice food."
    },
    {
        "Date":"2026-01-06",
        "Review":"good"
    },
    {
        "Date":"2026-01-06",
        "Review":"good \ud83d\udc4d\ud83c\udffb\ud83d\ude0a"
    },
    {
        "Date":"2026-01-06",
        "Review":"good price hy"
    },
    {
        "Date":"2026-01-06",
        "Review":"gpod"
    },
    {
        "Date":"2026-01-06",
        "Review":"excellent \ud83d\udc4c"
    },
    {
        "Date":"2026-01-06",
        "Review":"good service"
    },
    {
        "Date":"2026-01-06",
        "Review":"good"
    },
    {
        "Date":"2026-01-06",
        "Review":"supper"
    },
    {
        "Date":"2026-01-06",
        "Review":"Don't like the recent update to the Swiggy App... Food search no longer gives the option to view results restaurants as well as dishes. This used to be so convenient, to quickly view dishes that met the search criteria with a quick scroll, without needing to click into EACH restaurant to see if they even have what you are looking for. Not in the least user friendly :((( suggest roll back to search results they way they used to be."
    },
    {
        "Date":"2026-01-06",
        "Review":"not on time"
    },
    {
        "Date":"2026-01-06",
        "Review":"nice \ud83d\ude42\ud83d\udc4d"
    },
    {
        "Date":"2026-01-06",
        "Review":"very super swiggy very super"
    },
    {
        "Date":"2026-01-06",
        "Review":"Dinein cash utilisation is capped to only 200 per bill, whereas cashback amount is 10%. This means one can never use all the Dinein cash amount during redemption at restaurant.. And the Dinein cash will expire mandatorily, which means no value added for recurral visits to restaurants using dineout for redemption of Dinein cash amount."
    },
    {
        "Date":"2026-01-06",
        "Review":"ok"
    },
    {
        "Date":"2026-01-06",
        "Review":"good"
    },
    {
        "Date":"2026-01-06",
        "Review":"yes but need fast and I need item"
    },
    {
        "Date":"2026-01-06",
        "Review":"worst app they cancelled my order and refund not given I lost 1000 rupes...I want to complaint in social media"
    },
    {
        "Date":"2026-01-06",
        "Review":"good"
    },
    {
        "Date":"2026-01-06",
        "Review":"\u2763\ufe0f\u2763\ufe0f"
    },
    {
        "Date":"2026-01-06",
        "Review":"\u2764\ufe0f\u200d\ud83e\ude79\u2764\ufe0f\u200d\ud83e\ude79\u2764\ufe0f\u200d\ud83e\ude79"
    },
    {
        "Date":"2026-01-06",
        "Review":"good"
    },
    {
        "Date":"2026-01-06",
        "Review":"it's good"
    },
    {
        "Date":"2026-01-06",
        "Review":"\ud83d\udc4d"
    },
    {
        "Date":"2026-01-06",
        "Review":"initially it said 100 rupees discount but it was not implemented. they are lier"
    },
    {
        "Date":"2026-01-06",
        "Review":"good"
    },
    {
        "Date":"2026-01-06",
        "Review":"\ud83d\ude0a"
    },
    {
        "Date":"2026-01-06",
        "Review":"super"
    },
    {
        "Date":"2026-01-06",
        "Review":"great \ud83d\udc4d"
    },
    {
        "Date":"2026-01-06",
        "Review":"o no"
    },
    {
        "Date":"2026-01-06",
        "Review":"I recently realised why people like zomato more. Swiggy will keep you hungry at the time of crisis with no proper customer support."
    },
    {
        "Date":"2026-01-06",
        "Review":"fraudsters"
    },
    {
        "Date":"2026-01-06",
        "Review":"I love swiggy"
    },
    {
        "Date":"2026-01-06",
        "Review":"good"
    },
    {
        "Date":"2026-01-06",
        "Review":"good"
    },
    {
        "Date":"2026-01-06",
        "Review":"nice app is aslovs nice"
    },
    {
        "Date":"2026-01-06",
        "Review":"A very bad experience in this app The service is too poor please don't dwld this app"
    },
    {
        "Date":"2026-01-06",
        "Review":"u guys charge high and day by day no offers at all which is useful to customers .."
    },
    {
        "Date":"2026-01-06",
        "Review":"nice"
    },
    {
        "Date":"2026-01-06",
        "Review":"good"
    },
    {
        "Date":"2026-01-06",
        "Review":"nice food nd nice delivery"
    },
    {
        "Date":"2026-01-06",
        "Review":"good"
    },
    {
        "Date":"2026-01-06",
        "Review":"Very good"
    },
    {
        "Date":"2026-01-06",
        "Review":"everything else is fine but delivery is late"
    },
    {
        "Date":"2026-01-06",
        "Review":"super"
    },
    {
        "Date":"2026-01-06",
        "Review":"missing item"
    },
    {
        "Date":"2026-01-06",
        "Review":"good"
    },
    {
        "Date":"2026-01-06",
        "Review":"very nice \ud83d\udc4c"
    }
]