{
    "date": "2026-01-07",
    "topics": {
        "Positive Feedback": 289,
        "Delivery Speed": 7,
        "Delayed cold orders": 2,
        "High Pricing": 8,
        "Poor Food Quality": 15,
        "Unaccountable delivery delays": 36,
        "spyware risks": 0,
        "Unresponsive support": 29,
        "Cash on delivery unavailability": 2,
        "Missing items in delivery": 5,
        "Location detection failure": 1,
        "No promotions": 6,
        "App lag": 0,
        "Delivery personnel theft": 2,
        "Forced automatic types": 0,
        "Dark mode theme": 0,
        "Multiple account login restriction": 0,
        "Add egg-based food indicator": 0,
        "Failed UPI discount": 0,
        "Expired coupons": 0,
        "Worker Exploitation": 0,
        "App redundancy": 0,
        "Menu Originality": 0,
        "order cancellation": 8,
        "Blind accessibility issues": 0,
        "Monthly expense reports": 0,
        "Fraudulent practices": 8,
        "Credit card visibility": 0,
        "Delivery Area Restrictions": 1,
        "Address Change Issue": 0,
        "Near-expiry product delivery": 2,
        "User search flow": 0,
        "Vegetarian Filter": 0,
        "UI Simplification": 0,
        "Frequent login failures": 0,
        "Payment gateway failure": 0,
        "Negative Feedback": 4
    }
}